{
  "Classname": "BaseTank",
  "Description": "Entity_Description_here",
  "KeyDescriptions": [
    {
      "keyName": "spawnflags",
      "keyDescription": "Keyvalue_Description_here",
      "keyChoices": [
        {
          "choiceValue": "1 ",
          "choiceDescription": "Choice_Description_here"
        },
        {
          "choiceValue": "16",
          "choiceDescription": "Choice_Description_here"
        },
        {
          "choiceValue": "32",
          "choiceDescription": "Choice_Description_here"
        },
        {
          "choiceValue": "512",
          "choiceDescription": "Choice_Description_here"
        },
        {
          "choiceValue": "1024",
          "choiceDescription": "Choice_Description_here"
        }
      ]
    },
    {
      "keyName": "master",
      "keyDescription": "Keyvalue_Description_here",
      "keyChoices": []
    },
    {
      "keyName": "yawrate",
      "keyDescription": "Keyvalue_Description_here",
      "keyChoices": []
    },
    {
      "keyName": "yawrange",
      "keyDescription": "Keyvalue_Description_here",
      "keyChoices": []
    },
    {
      "keyName": "yawtolerance",
      "keyDescription": "Keyvalue_Description_here",
      "keyChoices": []
    },
    {
      "keyName": "pitchrate",
      "keyDescription": "Keyvalue_Description_here",
      "keyChoices": []
    },
    {
      "keyName": "pitchrange",
      "keyDescription": "Keyvalue_Description_here",
      "keyChoices": []
    },
    {
      "keyName": "pitchtolerance",
      "keyDescription": "Keyvalue_Description_here",
      "keyChoices": []
    },
    {
      "keyName": "barrel",
      "keyDescription": "Keyvalue_Description_here",
      "keyChoices": []
    },
    {
      "keyName": "barrely",
      "keyDescription": "Keyvalue_Description_here",
      "keyChoices": []
    },
    {
      "keyName": "barrelz",
      "keyDescription": "Keyvalue_Description_here",
      "keyChoices": []
    },
    {
      "keyName": "spritesmoke",
      "keyDescription": "Keyvalue_Description_here",
      "keyChoices": []
    },
    {
      "keyName": "spriteflash",
      "keyDescription": "Keyvalue_Description_here",
      "keyChoices": []
    },
    {
      "keyName": "spritescale",
      "keyDescription": "Keyvalue_Description_here",
      "keyChoices": []
    },
    {
      "keyName": "rotatesound",
      "keyDescription": "Keyvalue_Description_here",
      "keyChoices": []
    },
    {
      "keyName": "firerate",
      "keyDescription": "Keyvalue_Description_here",
      "keyChoices": []
    },
    {
      "keyName": "bullet_damage",
      "keyDescription": "Keyvalue_Description_here",
      "keyChoices": []
    },
    {
      "keyName": "persistence",
      "keyDescription": "Keyvalue_Description_here",
      "keyChoices": []
    },
    {
      "keyName": "firespread",
      "keyDescription": "Keyvalue_Description_here",
      "keyChoices": [
        {
          "choiceValue": "0",
          "choiceDescription": "Choice_Description_here"
        },
        {
          "choiceValue": "1",
          "choiceDescription": "Choice_Description_here"
        },
        {
          "choiceValue": "2",
          "choiceDescription": "Choice_Description_here"
        },
        {
          "choiceValue": "3",
          "choiceDescription": "Choice_Description_here"
        },
        {
          "choiceValue": "4",
          "choiceDescription": "Choice_Description_here"
        }
      ]
    },
    {
      "keyName": "minRange",
      "keyDescription": "Keyvalue_Description_here",
      "keyChoices": []
    },
    {
      "keyName": "maxRange",
      "keyDescription": "Keyvalue_Description_here",
      "keyChoices": []
    },
    {
      "keyName": "_minlight",
      "keyDescription": "Keyvalue_Description_here",
      "keyChoices": []
    },
    {
      "keyName": "relation_player",
      "keyDescription": "Keyvalue_Description_here",
      "keyChoices": [
        {
          "choiceValue": "-2",
          "choiceDescription": "Choice_Description_here"
        },
        {
          "choiceValue": "-1",
          "choiceDescription": "Choice_Description_here"
        },
        {
          "choiceValue": "0",
          "choiceDescription": "Choice_Description_here"
        },
        {
          "choiceValue": "1",
          "choiceDescription": "Choice_Description_here"
        },
        {
          "choiceValue": "2",
          "choiceDescription": "Choice_Description_here"
        },
        {
          "choiceValue": "3",
          "choiceDescription": "Choice_Description_here"
        }
      ]
    },
    {
      "keyName": "relation_none",
      "keyDescription": "Keyvalue_Description_here",
      "keyChoices": [
        {
          "choiceValue": "-2",
          "choiceDescription": "Choice_Description_here"
        },
        {
          "choiceValue": "-1",
          "choiceDescription": "Choice_Description_here"
        },
        {
          "choiceValue": "0",
          "choiceDescription": "Choice_Description_here"
        },
        {
          "choiceValue": "1",
          "choiceDescription": "Choice_Description_here"
        },
        {
          "choiceValue": "2",
          "choiceDescription": "Choice_Description_here"
        },
        {
          "choiceValue": "3",
          "choiceDescription": "Choice_Description_here"
        }
      ]
    },
    {
      "keyName": "relation_machine",
      "keyDescription": "Keyvalue_Description_here",
      "keyChoices": [
        {
          "choiceValue": "-2",
          "choiceDescription": "Choice_Description_here"
        },
        {
          "choiceValue": "-1",
          "choiceDescription": "Choice_Description_here"
        },
        {
          "choiceValue": "0",
          "choiceDescription": "Choice_Description_here"
        },
        {
          "choiceValue": "1",
          "choiceDescription": "Choice_Description_here"
        },
        {
          "choiceValue": "2",
          "choiceDescription": "Choice_Description_here"
        },
        {
          "choiceValue": "3",
          "choiceDescription": "Choice_Description_here"
        }
      ]
    },
    {
      "keyName": "relation_human_passive",
      "keyDescription": "Keyvalue_Description_here",
      "keyChoices": [
        {
          "choiceValue": "-2",
          "choiceDescription": "Choice_Description_here"
        },
        {
          "choiceValue": "-1",
          "choiceDescription": "Choice_Description_here"
        },
        {
          "choiceValue": "0",
          "choiceDescription": "Choice_Description_here"
        },
        {
          "choiceValue": "1",
          "choiceDescription": "Choice_Description_here"
        },
        {
          "choiceValue": "2",
          "choiceDescription": "Choice_Description_here"
        },
        {
          "choiceValue": "3",
          "choiceDescription": "Choice_Description_here"
        }
      ]
    },
    {
      "keyName": "relation_human_militar",
      "keyDescription": "Keyvalue_Description_here",
      "keyChoices": [
        {
          "choiceValue": "-2",
          "choiceDescription": "Choice_Description_here"
        },
        {
          "choiceValue": "-1",
          "choiceDescription": "Choice_Description_here"
        },
        {
          "choiceValue": "0",
          "choiceDescription": "Choice_Description_here"
        },
        {
          "choiceValue": "1",
          "choiceDescription": "Choice_Description_here"
        },
        {
          "choiceValue": "2",
          "choiceDescription": "Choice_Description_here"
        },
        {
          "choiceValue": "3",
          "choiceDescription": "Choice_Description_here"
        }
      ]
    },
    {
      "keyName": "relation_alien_militar",
      "keyDescription": "Keyvalue_Description_here",
      "keyChoices": [
        {
          "choiceValue": "-2",
          "choiceDescription": "Choice_Description_here"
        },
        {
          "choiceValue": "-1",
          "choiceDescription": "Choice_Description_here"
        },
        {
          "choiceValue": "0",
          "choiceDescription": "Choice_Description_here"
        },
        {
          "choiceValue": "1",
          "choiceDescription": "Choice_Description_here"
        },
        {
          "choiceValue": "2",
          "choiceDescription": "Choice_Description_here"
        },
        {
          "choiceValue": "3",
          "choiceDescription": "Choice_Description_here"
        }
      ]
    },
    {
      "keyName": "relation_alien_passive",
      "keyDescription": "Keyvalue_Description_here",
      "keyChoices": [
        {
          "choiceValue": "-2",
          "choiceDescription": "Choice_Description_here"
        },
        {
          "choiceValue": "-1",
          "choiceDescription": "Choice_Description_here"
        },
        {
          "choiceValue": "0",
          "choiceDescription": "Choice_Description_here"
        },
        {
          "choiceValue": "1",
          "choiceDescription": "Choice_Description_here"
        },
        {
          "choiceValue": "2",
          "choiceDescription": "Choice_Description_here"
        },
        {
          "choiceValue": "3",
          "choiceDescription": "Choice_Description_here"
        }
      ]
    },
    {
      "keyName": "relation_alien_monster",
      "keyDescription": "Keyvalue_Description_here",
      "keyChoices": [
        {
          "choiceValue": "-2",
          "choiceDescription": "Choice_Description_here"
        },
        {
          "choiceValue": "-1",
          "choiceDescription": "Choice_Description_here"
        },
        {
          "choiceValue": "0",
          "choiceDescription": "Choice_Description_here"
        },
        {
          "choiceValue": "1",
          "choiceDescription": "Choice_Description_here"
        },
        {
          "choiceValue": "2",
          "choiceDescription": "Choice_Description_here"
        },
        {
          "choiceValue": "3",
          "choiceDescription": "Choice_Description_here"
        }
      ]
    },
    {
      "keyName": "relation_alien_prey",
      "keyDescription": "Keyvalue_Description_here",
      "keyChoices": [
        {
          "choiceValue": "-2",
          "choiceDescription": "Choice_Description_here"
        },
        {
          "choiceValue": "-1",
          "choiceDescription": "Choice_Description_here"
        },
        {
          "choiceValue": "0",
          "choiceDescription": "Choice_Description_here"
        },
        {
          "choiceValue": "1",
          "choiceDescription": "Choice_Description_here"
        },
        {
          "choiceValue": "2",
          "choiceDescription": "Choice_Description_here"
        },
        {
          "choiceValue": "3",
          "choiceDescription": "Choice_Description_here"
        }
      ]
    },
    {
      "keyName": "relation_alien_predator",
      "keyDescription": "Keyvalue_Description_here",
      "keyChoices": [
        {
          "choiceValue": "-2",
          "choiceDescription": "Choice_Description_here"
        },
        {
          "choiceValue": "-1",
          "choiceDescription": "Choice_Description_here"
        },
        {
          "choiceValue": "0",
          "choiceDescription": "Choice_Description_here"
        },
        {
          "choiceValue": "1",
          "choiceDescription": "Choice_Description_here"
        },
        {
          "choiceValue": "2",
          "choiceDescription": "Choice_Description_here"
        },
        {
          "choiceValue": "3",
          "choiceDescription": "Choice_Description_here"
        }
      ]
    },
    {
      "keyName": "relation_insect",
      "keyDescription": "Keyvalue_Description_here",
      "keyChoices": [
        {
          "choiceValue": "-2",
          "choiceDescription": "Choice_Description_here"
        },
        {
          "choiceValue": "-1",
          "choiceDescription": "Choice_Description_here"
        },
        {
          "choiceValue": "0",
          "choiceDescription": "Choice_Description_here"
        },
        {
          "choiceValue": "1",
          "choiceDescription": "Choice_Description_here"
        },
        {
          "choiceValue": "2",
          "choiceDescription": "Choice_Description_here"
        },
        {
          "choiceValue": "3",
          "choiceDescription": "Choice_Description_here"
        }
      ]
    },
    {
      "keyName": "relation_player_ally",
      "keyDescription": "Keyvalue_Description_here",
      "keyChoices": [
        {
          "choiceValue": "-2",
          "choiceDescription": "Choice_Description_here"
        },
        {
          "choiceValue": "-1",
          "choiceDescription": "Choice_Description_here"
        },
        {
          "choiceValue": "0",
          "choiceDescription": "Choice_Description_here"
        },
        {
          "choiceValue": "1",
          "choiceDescription": "Choice_Description_here"
        },
        {
          "choiceValue": "2",
          "choiceDescription": "Choice_Description_here"
        },
        {
          "choiceValue": "3",
          "choiceDescription": "Choice_Description_here"
        }
      ]
    },
    {
      "keyName": "relation_player_bioweapon",
      "keyDescription": "Keyvalue_Description_here",
      "keyChoices": [
        {
          "choiceValue": "-2",
          "choiceDescription": "Choice_Description_here"
        },
        {
          "choiceValue": "-1",
          "choiceDescription": "Choice_Description_here"
        },
        {
          "choiceValue": "0",
          "choiceDescription": "Choice_Description_here"
        },
        {
          "choiceValue": "1",
          "choiceDescription": "Choice_Description_here"
        },
        {
          "choiceValue": "2",
          "choiceDescription": "Choice_Description_here"
        },
        {
          "choiceValue": "3",
          "choiceDescription": "Choice_Description_here"
        }
      ]
    },
    {
      "keyName": "relation_monster_bioweapon",
      "keyDescription": "Keyvalue_Description_here",
      "keyChoices": [
        {
          "choiceValue": "-2",
          "choiceDescription": "Choice_Description_here"
        },
        {
          "choiceValue": "-1",
          "choiceDescription": "Choice_Description_here"
        },
        {
          "choiceValue": "0",
          "choiceDescription": "Choice_Description_here"
        },
        {
          "choiceValue": "1",
          "choiceDescription": "Choice_Description_here"
        },
        {
          "choiceValue": "2",
          "choiceDescription": "Choice_Description_here"
        },
        {
          "choiceValue": "3",
          "choiceDescription": "Choice_Description_here"
        }
      ]
    },
    {
      "keyName": "relation_machine",
      "keyDescription": "Keyvalue_Description_here",
      "keyChoices": [
        {
          "choiceValue": "-2",
          "choiceDescription": "Choice_Description_here"
        },
        {
          "choiceValue": "-1",
          "choiceDescription": "Choice_Description_here"
        },
        {
          "choiceValue": "0",
          "choiceDescription": "Choice_Description_here"
        },
        {
          "choiceValue": "1",
          "choiceDescription": "Choice_Description_here"
        },
        {
          "choiceValue": "2",
          "choiceDescription": "Choice_Description_here"
        },
        {
          "choiceValue": "3",
          "choiceDescription": "Choice_Description_here"
        }
      ]
    }
  ],
  "Notes": [
    "Insert additional notes here"
  ],
  "Issues": [
    "Insert known issues here"
  ]
}